pycloudlib/__init__.py
pycloudlib/cloud.py
pycloudlib/config.py
pycloudlib/constants.py
pycloudlib/errors.py
pycloudlib/instance.py
pycloudlib/key.py
pycloudlib/py.typed
pycloudlib/result.py
pycloudlib/util.py
pycloudlib/azure/__init__.py
pycloudlib/azure/cloud.py
pycloudlib/azure/instance.py
pycloudlib/azure/security_types.py
pycloudlib/azure/util.py
pycloudlib/ec2/__init__.py
pycloudlib/ec2/cloud.py
pycloudlib/ec2/instance.py
pycloudlib/ec2/util.py
pycloudlib/ec2/vpc.py
pycloudlib/gce/__init__.py
pycloudlib/gce/cloud.py
pycloudlib/gce/errors.py
pycloudlib/gce/instance.py
pycloudlib/gce/util.py
pycloudlib/ibm/__init__.py
pycloudlib/ibm/_util.py
pycloudlib/ibm/cloud.py
pycloudlib/ibm/errors.py
pycloudlib/ibm/instance.py
pycloudlib/ibm_classic/__init__.py
pycloudlib/ibm_classic/cloud.py
pycloudlib/ibm_classic/errors.py
pycloudlib/ibm_classic/instance.py
pycloudlib/lxd/__init__.py
pycloudlib/lxd/_images.py
pycloudlib/lxd/cloud.py
pycloudlib/lxd/defaults.py
pycloudlib/lxd/instance.py
pycloudlib/oci/__init__.py
pycloudlib/oci/cloud.py
pycloudlib/oci/instance.py
pycloudlib/oci/utils.py
pycloudlib/openstack/__init__.py
pycloudlib/openstack/cloud.py
pycloudlib/openstack/errors.py
pycloudlib/openstack/instance.py
pycloudlib/qemu/__init__.py
pycloudlib/qemu/cloud.py
pycloudlib/qemu/instance.py
pycloudlib/qemu/util.py
pycloudlib/vmware/__init__.py
pycloudlib/vmware/cloud.py
pycloudlib/vmware/instance.py
tests/__init__.py
tests/conftest.py
tests/integration_tests/__init__.py
tests/integration_tests/test_public_api.py
tests/integration_tests/test_qemu.py
tests/integration_tests/ec2/__init__.py
tests/integration_tests/ec2/test_images.py
tests/integration_tests/gce/__init__.py
tests/integration_tests/gce/test_images.py
tests/integration_tests/gce/test_launch.py
tests/integration_tests/ibm/__init__.py
tests/integration_tests/ibm/test_launch.py
tests/integration_tests/oracle/__init__.py
tests/integration_tests/oracle/test_cluster.py
tests/unit_tests/__init__.py
pycloudlib-1!10.16.0.dist-info/LICENSE
pycloudlib-1!10.16.0.dist-info/METADATA
pycloudlib-1!10.16.0.dist-info/WHEEL
pycloudlib-1!10.16.0.dist-info/top_level.txt
pycloudlib-1!10.16.0.dist-info/zip-safe
pycloudlib-1!10.16.0.dist-info/RECORD
