Metadata-Version: 2.1
Name: pycloudlib
Version: 1!10.16.0
Summary: Python library to launch, interact, and snapshot cloud instances
Home-page: https://github.com/canonical/pycloudlib
Author: pycloudlib-devs
Author-email: pycloudlib-devs@lists.launchpad.net
License: GNU General Public License v3 (GPLv3)
Classifier: Development Status :: 4 - Beta
Classifier: Environment :: Console
Classifier: Intended Audience :: Developers
Classifier: Natural Language :: English
Classifier: Operating System :: POSIX :: Linux
Classifier: Programming Language :: Python :: 3 :: Only
Classifier: Topic :: Software Development :: Libraries :: Python Modules
Classifier: Topic :: Utilities
Requires-Python: >=3.8
License-File: LICENSE
Requires-Dist: azure-cli-core >=2.21.0
Requires-Dist: azure-identity
Requires-Dist: azure-mgmt-compute >=17
Requires-Dist: azure-mgmt-network >=16
Requires-Dist: azure-mgmt-resource >=15
Requires-Dist: boto3 >=1.14.20
Requires-Dist: botocore >=1.17.20
Requires-Dist: google-cloud-compute
Requires-Dist: googleapis-common-protos >=1.63.1
Requires-Dist: ibm-cloud-sdk-core >=3.14.0
Requires-Dist: ibm-platform-services
Requires-Dist: ibm-vpc <0.29.0,>=0.10
Requires-Dist: knack >=0.7.1
Requires-Dist: oci >=2.17.0
Requires-Dist: openstacksdk <1.5.0,>=1.1.0
Requires-Dist: paramiko >=2.9.2
Requires-Dist: protobuf
Requires-Dist: pyparsing <3.0.0,>=2
Requires-Dist: python-openstackclient >=5.2.1
Requires-Dist: pyyaml >=5.1
Requires-Dist: qemu.qmp >=0.0.3
Requires-Dist: requests >=2.22
Requires-Dist: Softlayer >=6.0.0
Requires-Dist: toml ==0.10
